angmom_suite/__init__.py
angmom_suite/__version__.py
angmom_suite/barrier.py
angmom_suite/basis.py
angmom_suite/cli.py
angmom_suite/crystal.py
angmom_suite/group.py
angmom_suite/magnetism.py
angmom_suite/model.py
angmom_suite/multi_electron.py
angmom_suite/optics.py
angmom_suite/optimisation.py
angmom_suite/utils.py
angmom_suite-1.29.1.dist-info/licenses/LICENSE
angmom_suite-1.29.1.dist-info/METADATA
angmom_suite-1.29.1.dist-info/WHEEL
angmom_suite-1.29.1.dist-info/entry_points.txt
angmom_suite-1.29.1.dist-info/top_level.txt
angmom_suite-1.29.1.dist-info/RECORD
