Metadata-Version: 2.4
Name: angmom_suite
Version: 1.29.1
Summary: A package for working with phenomenological spin and angular momentum operators
Home-page: https://gitlab.com/chilton-group/angmom_suite
Author: Chilton Group
Author-email: nicholas.chilton@manchester.ac.uk
Project-URL: Bug Tracker, https://gitlab.com/chilton-group/angmom_suite/issues
Project-URL: Documentation, https://chilton-group.gitlab.io/angmom_suite
Classifier: Programming Language :: Python :: 3
Classifier: License :: OSI Approved :: GNU General Public License v3 (GPLv3)
Classifier: Operating System :: OS Independent
Requires-Python: >=3.6
License-File: LICENSE
Requires-Dist: numpy
Requires-Dist: scipy
Requires-Dist: sympy<=1.12
Requires-Dist: matplotlib
Requires-Dist: h5py
Requires-Dist: hpc_suite>=1.8.0
Requires-Dist: jax>=0.4.25
Requires-Dist: jaxlib>=0.4.25
Requires-Dist: optax
Requires-Dist: molcas_suite>=1.34.2
Requires-Dist: pandas
Dynamic: author
Dynamic: author-email
Dynamic: classifier
Dynamic: description
Dynamic: description-content-type
Dynamic: home-page
Dynamic: license-file
Dynamic: project-url
Dynamic: requires-dist
Dynamic: requires-python
Dynamic: summary
